flask_ipban/__init__.py
flask_ipban/abuse_ipdb.py
flask_ipban/allowed.yaml
flask_ipban/get_lock.py
flask_ipban/ip_ban.py
flask_ipban/ip_record.py
flask_ipban/nuisance.yaml
flask_ipban/test.py
flask_ipban/test_persistence.py
flask_ipban-1.1.5.dist-info/LICENSE
flask_ipban-1.1.5.dist-info/METADATA
flask_ipban-1.1.5.dist-info/WHEEL
flask_ipban-1.1.5.dist-info/top_level.txt
flask_ipban-1.1.5.dist-info/RECORD
