Metadata-Version: 2.1
Name: flask-ipban
Version: 1.1.5
Summary: URL spam security for Flask.
Home-page: https://github.com/Martlark/flask-ipban
Author: Andrew Rowe
Author-email: rowe.andrew.d@gmail.com
License: Apache Software License
Download-URL: https://github.com/Martlark/flask-ipban/archive/1.1.5.tar.gz
Keywords: flask security spam url ban
Platform: UNKNOWN
Classifier: Development Status :: 5 - Production/Stable
Classifier: Intended Audience :: Developers
Classifier: Topic :: Software Development :: Libraries :: Python Modules
Classifier: License :: OSI Approved :: Apache Software License
Classifier: Programming Language :: Python
Classifier: Programming Language :: Python :: 3
Classifier: Programming Language :: Python :: 3.6
Classifier: Programming Language :: Python :: 3.7
Classifier: Programming Language :: Python :: 3.8
Classifier: Operating System :: POSIX
Classifier: Operating System :: MacOS
Classifier: Operating System :: Unix
Classifier: Operating System :: Microsoft :: Windows
Classifier: Framework :: Flask
